{"question": {"@xmlns": "http://schemas.assemblee-nationale.fr/referentiel", "@xmlns:xsi": "http://www.w3.org/2001/XMLSchema-instance", "@xsi:type": "QuestionGouvernement_Type", "uid": "QANR5L16QG1052", "identifiant": {"numero": "1052", "regime": "5eme Republique", "legislature": "16"}, "type": "QG", "indexationAN": {"rubrique": "\u00c9tat", "teteAnalyse": null, "analyses": {"analyse": "VIOLENCES URBAINES ET UNIT\u00c9 NATIONALE"}}, "auteur": {"identite": {"acteurRef": "PA720908", "mandatRef": "PM797556"}, "groupe": {"organeRef": "PO800514", "abrege": "HOR", "developpe": "Horizons et apparent\u00e9s"}}, "minInt": {"organeRef": "PO801856", "abrege": "Renouveau d\u00e9mocratique, porte-parole du Gouvernement", "developpe": "Minist\u00e8re aupr\u00e8s de la Premi\u00e8re ministre, charg\u00e9 du renouveau d\u00e9mocratique, porte-parole du Gouvernement"}, "minAttribs": {"minAttrib": {"infoJO": {"typeJO": "JO_DEBAT", "dateJO": "2023-07-05", "pageJO": null, "numJO": null, "urlLegifrance": null, "referenceNOR": null}, "denomination": {"organeRef": "PO801856", "abrege": "Renouveau d\u00e9mocratique, porte-parole du Gouvernement", "developpe": "Minist\u00e8re aupr\u00e8s de la Premi\u00e8re ministre, charg\u00e9 du renouveau d\u00e9mocratique, porte-parole du Gouvernement"}}}, "textesQuestion": null, "textesReponse": {"texteReponse": {"infoJO": {"typeJO": "JO_DEBAT", "dateJO": "2023-07-05", "pageJO": "6873", "numJO": null, "urlLegifrance": null, "referenceNOR": null}, "texte": "</p><p align=\"CENTER\"> VIOLENCES URBAINES ET UNIT\u00c9 NATIONALE <a name=PG19></a> </p><br><strong>Mme\u00a0la pr\u00e9sidente. </strong>La parole est \u00e0 Mme\u00a0Na\u00efma Moutchou.<br><br><strong>Mme\u00a0Na\u00efma Moutchou. </strong>Madame la Premi\u00e8re ministre, quand les parents s'habituent \u00e0 laisser faire leurs enfants, quand les enfants ne tiennent plus compte de leur parole, quand les enseignants tremblent devant leurs \u00e9l\u00e8ves et pr\u00e9f\u00e8rent les flatter, quand finalement les jeunes m\u00e9prisent les lois parce qu'ils ne reconnaissent plus l'autorit\u00e9 de rien ni de personne au-dessus d'eux, alors c'est le d\u00e9but de la tyrannie, disait Platon dans <i>La R\u00e9publique</i>.<br><br>Les violences urbaines de ces derniers jours, sympt\u00f4mes d'une France qui va mal, travers\u00e9e par une crise d'autorit\u00e9 et d'identit\u00e9, ne seront pas sans cons\u00e9quences.<br><br>\u00c0 court terme, nous devons bien s\u00fbr r\u00e9tablir l'ordre, mais il ne sert \u00e0 rien de r\u00e9parer ce qui a \u00e9t\u00e9 ab\u00eem\u00e9 si c'est pour que le chaos se reproduise.<br><br><strong>Mme\u00a0Caroline Parmentier.</strong> Comme \u00e0 chaque fois\u00a0!<br><br><strong>Mme\u00a0Na\u00efma Moutchou. </strong>Ce ne sont pas de nouveaux milliards dont les quartiers ont besoin. Ni la paix sociale ni le sentiment d'appartenance \u00e0 la nation ne s'ach\u00e8tent.<br><br><strong>Mme\u00a0Cl\u00e9mence Guett\u00e9.</strong> Il manque des services publics, des moyens\u00a0!<br><br><strong>Mme\u00a0Na\u00efma Moutchou. </strong>La responsabilit\u00e9 d'une partie de la classe politique dans ce qui se passe est immense. Une partie de la gauche a remis en cause nos institutions, justifiant l'usage de la force et de la violence.<br><br><strong>M.\u00a0Patrick Hetzel.</strong> Eh oui\u00a0! Et elle ne l'assume pas\u00a0!<br><br><strong>Mme\u00a0Na\u00efma Moutchou. </strong>Une partie de la gauche a nourri, chez les jeunes des quartiers, le sentiment d'ostracisation, la haine de la police et de l'autorit\u00e9, l'impression que la soci\u00e9t\u00e9 serait fondamentalement raciste. <i>(Applaudissements sur plusieurs bancs des groupes HOR, RE, LR et RN.)</i><br><br><strong>Mme\u00a0Sarah Legrain.</strong> Vous avez pris vos arguments chez le RN\u00a0?<br><br><strong>Mme\u00a0Na\u00efma Moutchou. </strong>Je l'ai vue \u00e0 l'\u0153uvre. Dans ma petite cit\u00e9 HLM du Val-d'Oise, j'ai entendu cette gauche nous dire\u00a0: \u00ab\u00a0La France vous rejette, vous n'y avez pas votre place\u00a0\u00bb.<br><br><strong>M.\u00a0Dino Cinieri.</strong> C'est vrai\u00a0!<br><br><strong>Mme\u00a0Na\u00efma Moutchou. </strong>Cette partie de la gauche n'a laiss\u00e9 \u00e0 ces populations aucun espoir de faire nation. Pire\u00a0: elle pense aujourd'hui tirer un b\u00e9n\u00e9fice politique du d\u00e9sordre. Elle finit pourtant par battre en retraite, car elle ne ma\u00eetrise rien.<br><br><strong>M.\u00a0Fr\u00e9d\u00e9ric Boccaletti.</strong> Ce sont des incendiaires\u00a0!<br><br><strong>Mme\u00a0Na\u00efma Moutchou. </strong>Et \u00e0 la fin, ce sont ses meilleurs ennemis, \u00e0 l'extr\u00eame droite, qui essaient d'en tirer parti. <i>(Exclamations sur les bancs du groupe LFI-NUPES.)</i><br><br><strong>Mme\u00a0Dani\u00e8le Obono.</strong> Quelle honte\u00a0!<br><br><strong>M.\u00a0St\u00e9phane Peu.</strong> Le temps de parole n'est-il pas d\u00e9pass\u00e9\u00a0?<br><br><strong>M.\u00a0Louis Boyard.</strong> L'impartialit\u00e9 de la pr\u00e9sidence est une chose merveilleuse\u2026<br><br><strong>Mme\u00a0Na\u00efma Moutchou. </strong>Mes chers coll\u00e8gues, une nation se sauve, elle ne se venge pas. Il est urgent que nous fassions front commun. Madame la Premi\u00e8re ministre, vous avez re\u00e7u les groupes politiques\u00a0: comment ensemble refaire nation\u00a0? (Applaudissements sur les bancs du groupe HOR et sur plusieurs bancs des groupes RE, LR et LIOT.)<br><br><strong>Mme\u00a0la pr\u00e9sidente. </strong>La parole est \u00e0 M.\u00a0le ministre d\u00e9l\u00e9gu\u00e9 charg\u00e9 du renouveau d\u00e9mocratique, porte-parole du Gouvernement.<br><br><strong>M.\u00a0Olivier V\u00e9ran,</strong><i> ministre d\u00e9l\u00e9gu\u00e9 charg\u00e9 du renouveau d\u00e9mocratique, porte-parole du Gouvernement. </i>Dans votre question, madame Moutchou, vous avez \u00e9voqu\u00e9, en les reliant \u00e0 des questions politiques, un panel d'\u00e9l\u00e9ments qui ont pu \u00e9ventuellement provoquer les sc\u00e8nes de violence auxquelles nous avons assist\u00e9. Je vais essayer de vous r\u00e9pondre.<br><br>Je rappelle d'abord quelle a \u00e9t\u00e9 l'action du Gouvernement depuis le premier jour\u00a0: premi\u00e8rement, restaurer l'ordre\u00a0;\u2026<br><br><strong>M.\u00a0Maxime Minot.</strong> Deuxi\u00e8mement, ne rien faire\u00a0! Troisi\u00e8mement, surtout ne pas d\u00e9roger \u00e0 cette r\u00e8gle\u00a0!<br><br><strong>M.\u00a0Olivier V\u00e9ran,</strong><i> ministre d\u00e9l\u00e9gu\u00e9 . </i>\u2026deuxi\u00e8mement, maintenir l'ordre\u00a0; troisi\u00e8mement, ne jamais perdre de vue ces objectifs de pr\u00e9servation de l'ordre pour les territoires.<br><br><strong>Mme\u00a0Sophia Chikirou.</strong> La paix et la justice, \u00e7a ne compte pas chez vous\u00a0?<br><br><strong>M.\u00a0Olivier V\u00e9ran,</strong><i> ministre d\u00e9l\u00e9gu\u00e9 . </i>Les premi\u00e8res victimes sont les commer\u00e7ants, les pompiers, les gendarmes, les policiers ainsi que les habitants des quartiers. Ceux-ci ont vu des services publics incendi\u00e9s, des magasins saccag\u00e9s, des vitrines \u00e9ventr\u00e9es\u2026<br><br><strong>M.\u00a0Sylvain Maillard.</strong> Il a raison\u00a0!<br><br><strong>M.\u00a0Olivier V\u00e9ran,</strong><i> ministre d\u00e9l\u00e9gu\u00e9 . </i>\u2026et se sentent eux-m\u00eames victimes de l'image que ces jeunes ont pu renvoyer de l'ensemble des quartiers.<br><br>Il faudra \u00e9videmment nous interroger, et il ne s'agit pas d'excuser \u2013\u00a0ce n'est d'ailleurs pas le sens de votre question. Le garde des sceaux l'a indiqu\u00e9, pr\u00e8s de 4\u00a0000\u00a0personnes ont \u00e9t\u00e9 interpell\u00e9es. Beaucoup comparaissent d\u00e9j\u00e0 devant la justice\u00a0; d'autres le feront dans les prochains jours. Il sera int\u00e9ressant de regarder \u00e0 qui nous avons affaire. Comment se fait-il que des jeunes de 12 ou 13\u00a0ans se soient retrouv\u00e9s, au milieu de la nuit, avec un bidon d'essence pour mettre le feu \u00e0 un pavillon ou une pierre \u00e0 la main pour casser une vitrine\u00a0?<br><br><strong>Mme\u00a0Dani\u00e8le Obono.</strong> Augmentez les salaires\u00a0!<br><br><strong>Mme\u00a0Aur\u00e9lie Trouv\u00e9.</strong> Arr\u00eatez le travail de nuit\u00a0!<br><br><strong>M.\u00a0Olivier V\u00e9ran,</strong><i> ministre d\u00e9l\u00e9gu\u00e9 . </i>Il a \u00e9t\u00e9 question, \u00e0 juste titre, de la responsabilit\u00e9 parentale. <i>(Mme\u00a0Aur\u00e9lie Trouv\u00e9 s'exclame.) </i>Madame Trouv\u00e9, je ne crois pas qu'il faille chercher, dans les cris, une r\u00e9ponse toute faite. Nous avons besoin d'apprendre pour que cela ne se reproduise plus. Vous avez raison de dire, madame Moutchou, que la r\u00e9ponse ne sera pas dans un d\u00e9ferlement de d\u00e9penses publiques dans ces quartiers. (Exclamations sur quelques bancs du groupe LFI-NUPES.)<br><br><strong>Mme\u00a0Dani\u00e8le Obono.</strong> Ah, surtout pas\u00a0!<br><br><strong>M.\u00a0Olivier V\u00e9ran,</strong><i> ministre d\u00e9l\u00e9gu\u00e9 . </i>En tout cas, il nous faudra arriver \u00e0 saisir les tenants et les aboutissants. Je le redis, comment des jeunes de cet \u00e2ge ont-ils pu en arriver l\u00e0\u00a0?<br><br><strong>Mme\u00a0Caroline Parmentier.</strong> Vous n'avez pas encore compris\u00a0?<br><br><strong>M.\u00a0Olivier V\u00e9ran,</strong><i> ministre d\u00e9l\u00e9gu\u00e9 . </i>Je termine ma r\u00e9ponse sur une note plus politique. Les habitants des quartiers que vous avez \u00e9voqu\u00e9s n'ont peut-\u00eatre pas de parti politique en propre, mais ils ont de la m\u00e9moire. Ils sauront se souvenir, t\u00f4t ou tard, de qui \u00e9tait \u00e0 leurs c\u00f4t\u00e9s pour restaurer l'ordre et les services, et de qui a tent\u00e9 de les instrumentaliser. <i>(Applaudissements sur quelques bancs des groupes RE et LR. \u2013\u00a0Exclamations sur quelques bancs du groupe LFI-NUPES.)</i><br><br><strong>Mme\u00a0Dani\u00e8le Obono.</strong> Oui, six ans de macronisme, ils s'en souviendront\u00a0!<br> <p>"}}, "cloture": {"codeCloture": "REP_PUB", "libelleCloture": "R\u00e9ponse publi\u00e9e", "dateCloture": "2023-07-05", "infoJO": {"typeJO": "JO_DEBAT", "dateJO": "2023-07-05", "pageJO": "6873", "numJO": null, "urlLegifrance": null, "referenceNOR": null}}}}