{"question": {"@xmlns": "http://schemas.assemblee-nationale.fr/referentiel", "@xmlns:xsi": "http://www.w3.org/2001/XMLSchema-instance", "@xsi:type": "QuestionGouvernement_Type", "uid": "QANR5L16QG727", "identifiant": {"numero": "727", "regime": "5eme Republique", "legislature": "16"}, "type": "QG", "indexationAN": {"rubrique": "personnes handicap\u00e9es", "teteAnalyse": null, "analyses": {"analyse": "PARCOURS DES JEUNES ADULTES HANDICAP\u00c9S"}}, "auteur": {"identite": {"acteurRef": "PA720696", "mandatRef": "PM796989"}, "groupe": {"organeRef": "PO800532", "abrege": "LIOT", "developpe": "Libert\u00e9s, Ind\u00e9pendants, Outre-mer et Territoires"}}, "minInt": {"organeRef": "PO801893", "abrege": "Personnes handicap\u00e9es", "developpe": "Minist\u00e8re aupr\u00e8s du ministre des solidarit\u00e9s, de l'autonomie et des personnes handicap\u00e9es, charg\u00e9 des personnes handicap\u00e9es"}, "minAttribs": {"minAttrib": {"infoJO": {"typeJO": "JO_DEBAT", "dateJO": "2023-04-05", "pageJO": null, "numJO": null, "urlLegifrance": null, "referenceNOR": null}, "denomination": {"organeRef": "PO801893", "abrege": "Personnes handicap\u00e9es", "developpe": "Minist\u00e8re aupr\u00e8s du ministre des solidarit\u00e9s, de l'autonomie et des personnes handicap\u00e9es, charg\u00e9 des personnes handicap\u00e9es"}}}, "textesQuestion": null, "textesReponse": {"texteReponse": {"infoJO": {"typeJO": "JO_DEBAT", "dateJO": "2023-04-05", "pageJO": "3444", "numJO": null, "urlLegifrance": null, "referenceNOR": null}, "texte": "</p><p align=\"CENTER\"> PARCOURS DES JEUNES ADULTES HANDICAP\u00c9S <a name=PG3></a> </p><br><strong>Mme\u00a0la pr\u00e9sidente. </strong>La parole est \u00e0 Mme\u00a0B\u00e9atrice Descamps.<br><br><strong>Mme\u00a0B\u00e9atrice Descamps. </strong>Ma question s\u2019adresse \u00e0 Mme\u00a0la ministre d\u00e9l\u00e9gu\u00e9e charg\u00e9e des personnes handicap\u00e9es. Pour protecteur qu\u2019il soit, l\u2019amendement \u00ab\u00a0Creton\u00a0\u00bb a pour effet de maintenir, dans des \u00e9tablissements sp\u00e9cialis\u00e9s pour enfants, des jeunes adultes qui ont d\u00e9pass\u00e9 la limite d\u2019\u00e2ge administrative de 20\u00a0ans, et qui attendent une place dans une structure pour adultes. Faute de structures adapt\u00e9es, de nombreux jeunes restent en institut m\u00e9dico-\u00e9ducatif (IME) parfois jusqu\u2019\u00e0 28\u00a0ans. Ils y d\u00e9veloppent un mal-\u00eatre, des troubles du comportement ou des absences \u00e0 r\u00e9p\u00e9tition. Parall\u00e8lement, l\u2019accueil prolong\u00e9 des plus \u00e2g\u00e9s en IME bloque l\u2019arriv\u00e9e des plus jeunes, les privant d\u2019une prise en charge pourtant indispensable. <br><br>Cette organisation impose d\u2019importantes contraintes aux \u00e9quipes, qui doivent d\u00e9multiplier l\u2019offre d\u2019activit\u00e9s \u00e9ducatives et de soutien m\u00e9dico-social \u2013\u00a0sans compter les difficult\u00e9s juridiques que peut causer la cohabitation entre enfants mineurs et jeunes adultes.<br><br>Con\u00e7u comme un dispositif transitoire, l\u2019amendement \u00ab\u00a0Creton\u00a0\u00bb ne permet que de d\u00e9caler les ruptures de parcours et les retours \u00e0 domicile sans accompagnement.<br><br><strong>M.\u00a0Arthur Delaporte.</strong> Elle a raison\u00a0!<br><br><strong>Mme\u00a0B\u00e9atrice Descamps. </strong>Les familles que je rencontre r\u00e9guli\u00e8rement souffrent plus encore lorsqu\u2019elles voient leurs enfants devenir adolescents, car elles savent que quelques ann\u00e9es plus tard, ils n'auront pas acc\u00e8s \u00e0 une r\u00e9ponse adapt\u00e9e \u2013\u00a0j\u2019ai d\u2019ailleurs une pens\u00e9e pour les mamans de jeunes autistes que j\u2019ai re\u00e7ues tr\u00e8s r\u00e9cemment. J\u2019\u00e9voque ici des jeunes pour lesquels les solutions alternatives ne sont pas envisageables. Rappelons-le\u00a0: il faut attendre dix \u00e0 quinze ans pour obtenir une place dans un \u00e9tablissement pour adultes. Quelles mesures comptez-vous prendre pour r\u00e9duire ces d\u00e9s\u00e9quilibres et apporter des r\u00e9ponses concr\u00e8tes \u00e0 ces familles et \u00e0 ces jeunes\u00a0? <i>(Applaudissements sur les bancs du groupe LIOT et sur plusieurs bancs des groupes RE et Dem.)</i><br><br><strong>Mme\u00a0la pr\u00e9sidente. </strong>La parole est \u00e0 Mme\u00a0la ministre d\u00e9l\u00e9gu\u00e9e charg\u00e9e des personnes handicap\u00e9es.<br><br><strong>Mme\u00a0Genevi\u00e8ve Darrieussecq,</strong><i> ministre d\u00e9l\u00e9gu\u00e9e charg\u00e9e des personnes handicap\u00e9es. </i>Vous posez une question importante et difficile. Ma position est claire\u00a0: les adultes n'ont rien \u00e0 faire dans des \u00e9tablissements pour enfants. Nous devons \u00eatre proactifs pour changer la situation.<br><br><strong>M.\u00a0Maxime Minot.</strong> Il serait temps\u00a0!<br><br><strong>Mme\u00a0Genevi\u00e8ve Darrieussecq,</strong><i> ministre d\u00e9l\u00e9gu\u00e9e. </i>Soyons honn\u00eates, cela ne se fera pas en un jour.<br><br><strong>M.\u00a0Maxime Minot.</strong> Cela fait six ans que vous \u00eates au pouvoir\u00a0!<br><br><strong>Mme\u00a0Genevi\u00e8ve Darrieussecq,</strong><i> ministre d\u00e9l\u00e9gu\u00e9e . </i>Nous devons r\u00e9pondre au mieux aux besoins des personnes concern\u00e9es\u00a0: certaines peuvent entrer dans l'emploi, d'autres ne le peuvent pas mais doivent b\u00e9n\u00e9ficier d'accompagnements sp\u00e9cifiques, voire de structures sp\u00e9cifiques. Je souhaite que chaque cas soit \u00e9valu\u00e9 individuellement, et que nous trouvions des r\u00e9ponses. Notez que la situation actuelle, outre qu'elle n'est pas satisfaisante pour les jeunes adultes, est \u00e9galement contraignante pour les jeunes, puisque les places en IME auxquelles ils pourraient pr\u00e9tendre sont bloqu\u00e9es.<br><br>Nous avons devant nous un important travail. J'esp\u00e8re que la prochaine Conf\u00e9rence nationale du handicap nous donnera les moyens d'avancer. Il faut \u00e9valuer plus pr\u00e9cocement les jeunes dans leurs capacit\u00e9s et leurs comp\u00e9tences, leur proposer plus t\u00f4t des formations et leur construire des parcours de sortie des IME en douceur, pour se diriger vers des \u00e9tablissements et services d\u2019aide par le travail (Esat) ou vers le travail en milieu ordinaire. Les cas les plus complexes doivent trouver des solutions en institution. <i>(Applaudissements sur quelques bancs des groupes RE et Dem.)</i><br> <p>"}}, "cloture": {"codeCloture": "REP_PUB", "libelleCloture": "R\u00e9ponse publi\u00e9e", "dateCloture": "2023-04-05", "infoJO": {"typeJO": "JO_DEBAT", "dateJO": "2023-04-05", "pageJO": "3444", "numJO": null, "urlLegifrance": null, "referenceNOR": null}}}}